google/cloud/securitycenter/__init__.py
google/cloud/securitycenter/gapic_version.py
google/cloud/securitycenter/py.typed
google/cloud/securitycenter_v1/__init__.py
google/cloud/securitycenter_v1/gapic_metadata.json
google/cloud/securitycenter_v1/gapic_version.py
google/cloud/securitycenter_v1/py.typed
google/cloud/securitycenter_v1/services/__init__.py
google/cloud/securitycenter_v1/services/security_center/__init__.py
google/cloud/securitycenter_v1/services/security_center/async_client.py
google/cloud/securitycenter_v1/services/security_center/client.py
google/cloud/securitycenter_v1/services/security_center/pagers.py
google/cloud/securitycenter_v1/services/security_center/transports/__init__.py
google/cloud/securitycenter_v1/services/security_center/transports/base.py
google/cloud/securitycenter_v1/services/security_center/transports/grpc.py
google/cloud/securitycenter_v1/services/security_center/transports/grpc_asyncio.py
google/cloud/securitycenter_v1/services/security_center/transports/rest.py
google/cloud/securitycenter_v1/services/security_center/transports/rest_base.py
google/cloud/securitycenter_v1/types/__init__.py
google/cloud/securitycenter_v1/types/access.py
google/cloud/securitycenter_v1/types/application.py
google/cloud/securitycenter_v1/types/asset.py
google/cloud/securitycenter_v1/types/attack_exposure.py
google/cloud/securitycenter_v1/types/attack_path.py
google/cloud/securitycenter_v1/types/backup_disaster_recovery.py
google/cloud/securitycenter_v1/types/bigquery_export.py
google/cloud/securitycenter_v1/types/cloud_armor.py
google/cloud/securitycenter_v1/types/cloud_dlp_data_profile.py
google/cloud/securitycenter_v1/types/cloud_dlp_inspection.py
google/cloud/securitycenter_v1/types/compliance.py
google/cloud/securitycenter_v1/types/connection.py
google/cloud/securitycenter_v1/types/contact_details.py
google/cloud/securitycenter_v1/types/container.py
google/cloud/securitycenter_v1/types/database.py
google_cloud_securitycenter-1.41.0.dist-info/licenses/LICENSE
google_cloud_securitycenter-1.41.0.dist-info/METADATA
google_cloud_securitycenter-1.41.0.dist-info/WHEEL
google_cloud_securitycenter-1.41.0.dist-info/top_level.txt
google_cloud_securitycenter-1.41.0.dist-info/RECORD
